{"name":"Looking up the definition of \u0027pear\u0027","testSteps":[{"number":1,"description":"Given the user is on the Wikionary home page","duration":34,"startTime":1468945105399,"result":"SKIPPED","children":[{"number":2,"description":"Is the home page","duration":23,"startTime":1468945105410,"result":"IGNORED"}]},{"number":3,"description":"When the user looks up the definition of the word \u0027pear\u0027","duration":57,"startTime":1468945105434,"result":"SKIPPED","children":[{"number":4,"description":"Looks for: \u003cspan class\u003d\u0027step-parameter\u0027\u003epear\u003c/span\u003e","duration":49,"startTime":1468945105441,"result":"IGNORED","children":[{"number":5,"description":"Enters: \u003cspan class\u003d\u0027step-parameter\u0027\u003epear\u003c/span\u003e","duration":28,"startTime":1468945105444,"result":"IGNORED"},{"number":6,"description":"Starts search","duration":17,"startTime":1468945105473,"result":"IGNORED"}]}]},{"number":7,"description":"Then they should see the definition \u0027An edible fruit produced by the pear tree, similar to an apple but elongated towards the stem.\u0027","duration":5,"startTime":1468945105491,"result":"SKIPPED","children":[{"number":8,"description":"Should see definition: \u003cspan class\u003d\u0027step-parameter\u0027\u003eAn edible fruit produced by the pear tree, similar to an apple but elongated towards the stem.\u003c/span\u003e","duration":1,"startTime":1468945105494,"result":"IGNORED"}]}],"userStory":{"id":"LookupADefinition","storyName":"Lookup a definition","path":"stories/consult_dictionary/LookupADefinition.story","narrative":"In order to talk better\nAs a n English student\nI want to look up word definitions","type":"story"},"title":"Looking up the definition of \u0027pear\u0027","tags":[{"name":"Consult dictionary/Lookup a definition","type":"story"},{"name":"Consult dictionary","type":"feature"}],"startTime":1468945105363,"duration":160,"annotatedResult":"SUCCESS","sessionId":"536628fd-5e5a-4867-9cfb-ef1bd791541c","driver":"firefox","manual":false,"result":"SUCCESS"}